Metadata-Version: 1.1
Name: pycorrelate
Version: 0.3
Summary: Fast and accurate timestamps correlation in python.
Home-page: https://github.com/tritemio/pycorrelate
Author: Antonino Ingargiola
Author-email: tritemio@gmail.com
License: GNU General Public License v3
Keywords: pycorrelate
Platform: UNKNOWN
Classifier: Development Status :: 2 - Pre-Alpha
Classifier: Intended Audience :: Developers
Classifier: License :: OSI Approved :: GNU General Public License v3 (GPLv3)
Classifier: Natural Language :: English
Classifier: Programming Language :: Python :: 3
Classifier: Programming Language :: Python :: 3.5
Classifier: Programming Language :: Python :: 3.6
